metaflow_extensions/mpi/plugins/mfextinit_mpi.py
metaflow_extensions/mpi/plugins/mpi_decorator.py
metaflow_mpi-0.0.3.dist-info/LICENSE
metaflow_mpi-0.0.3.dist-info/METADATA
metaflow_mpi-0.0.3.dist-info/WHEEL
metaflow_mpi-0.0.3.dist-info/top_level.txt
metaflow_mpi-0.0.3.dist-info/RECORD
