Metadata-Version: 2.1
Name: metaflow-mpi
Version: 0.0.3
Summary: An EXPERIMENTAL MPI decorator for Metaflow
Author: Eddie Mattia
Author-email: eddie@outerbounds.com
License-File: LICENSE
Requires-Dist: metaflow
